{
  "updated_at": "2026-07-02T08:53:44.625844",
  "tip": "نصيحة اليوم: حافظ على نشاطك البدني وتناول غذاء متوازن.",
  "articles": [
    {
      "source": {
        "id": null,
        "name": "Akhbarona.com"
      },
      "author": "أخبارنا المغربية - وكالات",
      "title": "تحذير طبي: التدخين الإلكتروني يهدد صحة القلب والأوعية الدموية",
      "description": "تتزايد الأدلة العلمية التي تدحض الاعتقاد بأن السجائر الإلكترونية تمثل بديلاً آمناً للتدخين التقليدي، بعدما كشفت دراسات حديثة عن ارتباط استخدامها بارتفاع خطر الإصابة بأمراض",
      "url": "https://www.akhbarona.com/health/428472.html",
      "urlToImage": "https://www.akhbarona.com/thumbs/article_large/7/0/7972681d-60b9-44ff-89c2-8d263a63cbf2_1782864404.webp",
      "publishedAt": "2026-07-01T01:32:56Z",
      "content": ".\r\n .\r\n \" \" (FDA) .\r\n .\r\n Circulation: Arrhythmia and Electrophysiology .\r\n . .\r\n .\r\n ."
    },
    {
      "source": {
        "id": null,
        "name": "Sarabic.ae"
      },
      "author": "سبوتنيك عربي",
      "title": "الخارجية الإيرانية تنفي عقد محادثات فنية بين طهران وواشنطن في الدوحة",
      "description": "نفى نائب وزير الخارجية الإيراني وكبير المفاوضين، كاظم غريب آبادي، اليوم الاثنين، صحة التقارير التي تحدثت عن عقد محادثات فنية بين فرق العمل الإيرانية والأمريكية في الدوحة خلال الأيام المقبلة، مؤكدا أن مثل هذه الاجتماعات لم تُدرج على جدول أعمال هذا الأسبوع.",
      "url": "https://sarabic.ae/20260629/%D8%A7%D9%84%D8%AE%D8%A7%D8%B1%D8%AC%D9%8A%D8%A9-%D8%A7%D9%84%D8%A5%D9%8A%D8%B1%D8%A7%D9%86%D9%8A%D8%A9-%D8%AA%D9%86%D9%81%D9%8A-%D8%B9%D9%82%D8%AF-%D9%85%D8%AD%D8%A7%D8%AF%D8%AB%D8%A7%D8%AA-%D9%81%D9%86%D9%8A%D8%A9-%D8%A8%D9%8A%D9%86-%D8%B7%D9%87%D8%B1%D8%A7%D9%86-%D9%88%D9%88%D8%A7%D8%B4%D9%86%D8%B7%D9%86-%D9%81%D9%8A-%D8%A7%D9%84%D8%AF%D9%88%D8%AD%D8%A9-1114806772.html",
      "urlToImage": "https://cdn.img.sarabic.ae/img/07ea/06/1d/1114806927_0:0:1653:929_2072x0_60_0_0_d3d7f0265bf7c3d12f20da609fb36841.jpg.webp",
      "publishedAt": "2026-06-29T11:47:36Z",
      "content": "https://sarabic.ae/20260629/-----------1114806772.html\r\nhttps://cdn.img.sarabic.ae/img/07ea/06/1d/1114806927_0:0:1653:929_1920x0_80_0_0_b519957986009bfd18dd06301d0b6ff2.jpg.webp\r\n .: \" \" \"\" . . 29 30… [+318 chars]"
    },
    {
      "source": {
        "id": null,
        "name": "Aljazeera.net"
      },
      "author": "محمد عبد العظيم",
      "title": "ليست رفاهية كما تظنين.. ماذا تفعل زيوت الكيوتيكل بأظافرك؟",
      "description": "هل يمكن لبضع قطرات من زيت صغير حول الظفر أن تغير صحة يديك ومظهرهما بالكامل؟",
      "url": "https://www.aljazeera.net/women/2026/6/28/%d8%b2%d9%8a%d9%88%d8%aa-%d8%a7%d9%84%d9%83%d9%8a%d9%88%d8%aa%d9%8a%d9%83%d9%84-%d8%b3%d8%b1-%d8%a7%d9%84%d8%a3%d8%b8%d8%a7%d9%81%d8%b1-%d8%a7%d9%84%d9%82%d9%88%d9%8a%d8%a9",
      "urlToImage": "https://www.aljazeera.net/wp-content/uploads/2026/06/zywt-alkywtykl-1782637333.png?resize=1920%2C1440",
      "publishedAt": "2026-06-28T06:15:31Z",
      "content": "|\r\n. ( ) .\r\n .\r\nlist of 4 items<ul><li>list 1 of 4 .. </li><li>list 2 of 4 .. </li><li>list 3 of 4 .. </li><li>list 4 of 4 .. </li></ul>end of list\r\n \" \" . .\r\n \"\" . .\r\n . .\r\n ()\r\n.\r\n \"\" . .\r\n . .\r\n .… [+58 chars]"
    },
    {
      "source": {
        "id": null,
        "name": "محليات"
      },
      "author": "العين - وام",
      "title": "70 جلسة وعرضاً علمياً في مؤتمر علم الأورام بأبوظبي",
      "description": "أعلنت «صحة» في أبوظبي عن انطلاق مؤتمر «Best of ASCO 2026 UAE» التعليمي المتخصص في علم الأورام، وتنظمه إدارة الأورام في مستشفى توام يومي 27 و28 يونيو الجاري بمدينة العين.يشارك في المؤتمر نخبة من المتخصصين في مجال الأورام من مختلف أنحاء الدولة، لمراجعة أبرز",
      "url": "https://www.emaratalyoum.com/local-section/health/2026-06-28-1.2059888",
      "urlToImage": "https://www.emaratalyoum.com/polopoly_fs/1.2059884.1782588092!/image/image.jpeg",
      "publishedAt": "2026-06-28T00:08:04Z",
      "content": "«» «Best of ASCO 2026 UAE» 27 28 .\r\n .\r\n 47 «ASCO» 15 .\r\n .\r\n «Best of ASCO 2026 UAE» «» .\r\n «Best of ASCO 2026 UAE» ."
    },
    {
      "source": {
        "id": "cnn",
        "name": "CNN"
      },
      "author": "CNN بالعربية",
      "title": "أول تعليق من الاتحاد المصري على مزاعم خلاف هيثم حسن مع مدرب المنتخب",
      "description": "نفى مصطفى أبو زهرة، عضو الاتحاد المصري لكرة القدم وأحد أفراد بعثة منتخب \"الفراعنة\" في أمريكا، صحة تقارير صحفية قد زعمت دخول اللاعب هيثم حسن في خلاف مع مدربه حسام حسن.",
      "url": "https://arabic.cnn.com/sport/article/2026/06/28/haissem-hassan-hossam-hassan-egypt",
      "urlToImage": "https://cnn-arabic-images.cnn.io/cloudinary/image/upload/x_0,y_59,w_5875,h_3305,c_crop/w_1920,h_1008,c_fill,q_auto,g_center/t_cnnarabic_watermark_logo_v5/cnnarabic/2026/06/28/images/336805.jpg",
      "publishedAt": "2026-06-27T23:21:32Z",
      "content": ""
    },
    {
      "source": {
        "id": null,
        "name": "Aljazeera.net"
      },
      "author": "الجزيرة نت",
      "title": "الدقيقة 93.. هل ظلم حكم الفيديو المساعد منتخب إيران أمام مصر؟",
      "description": "فجر إلغاء هدف إيران في الدقيقة 93 بحجة التسلل بعد العودة إلى تقنية الفار جدلًا واسعًا، قبل أن تنتهي المباراة بالتعادل 1-1 وتأهل مصر، وسط نقاشات حول صحة القرار التحكيمي وتطبيق قانون التسلل.",
      "url": "https://www.aljazeera.net/sport/2026/6/27/%d8%a7%d9%84%d8%af%d9%82%d9%8a%d9%82%d8%a9-93-%d9%87%d9%84-%d8%b8%d9%84%d9%85-%d8%ad%d9%83%d9%85-%d8%a7%d9%84%d9%81%d9%8a%d8%af%d9%8a%d9%88-%d8%a7%d9%84%d9%85%d8%b3%d8%a7%d8%b9%d8%af",
      "urlToImage": "https://www.aljazeera.net/wp-content/uploads/2026/06/1221-1782556090.jpg?resize=1920%2C1280&quality=80",
      "publishedAt": "2026-06-27T10:11:15Z",
      "content": "|\r\n93 (VAR) 2026.\r\n .\r\n.\r\nlist of 2 itemsend of list\r\n (VAR) .\r\n (11) .\r\n .\r\n .\r\n .\r\n .\r\n .\r\n . .\r\n .\r\n .\r\n (1-1) 32 .\r\n (VAR) .\r\n .\r\n \"\" \" 100%\" \" \" .\r\n .\r\n .\r\n .\r\n \" \" .\r\n ."
    },
    {
      "source": {
        "id": null,
        "name": "Aljazeera.net"
      },
      "author": "محمد صلاح",
      "title": "شهيتك تقل مع اشتداد الحر؟.. 5 نصائح غذائية لصيف أكثر صحة",
      "description": "قد يبدو انخفاض الشهية في الصيف أمرا عابرا، لكن ما يحدث داخل جسمك قد يكون فرصة لتحسين عاداتك الغذائية، أو الوقوع في أخطاء لا تنتبه إليها.",
      "url": "https://www.aljazeera.net/lifestyle/2026/6/27/5-%d9%86%d8%b5%d8%a7%d8%a6%d8%ad-%d8%ba%d8%b0%d8%a7%d8%a6%d9%8a%d8%a9-%d9%84%d8%b5%d9%8a%d9%81-%d8%a3%d9%83%d8%ab%d8%b1-%d8%b5%d8%ad%d8%a9",
      "urlToImage": "https://www.aljazeera.net/wp-content/uploads/2026/06/shhytk-fy-alsyf-1782561396.png?resize=1200%2C675",
      "publishedAt": "2026-06-27T09:38:37Z",
      "content": ". .\r\n \"\" .\r\nlist of 4 items<ul><li>list 1 of 4 .. </li><li>list 2 of 4 .. </li><li>list 3 of 4 .. 10 </li><li>list 4 of 4 .. </li></ul>end of list\r\n . \r\n ()\r\n. :\r\n . .\r\n .\r\n . \" \" .\r\n . .\r\n . . .\r\n (… [+103 chars]"
    },
    {
      "source": {
        "id": null,
        "name": "BBC News"
      },
      "author": "https://www.facebook.com/bbcnews",
      "title": "العقم عند الرجال: لماذا يتأخر التشخيص ويغيب الدعم؟",
      "description": "رغم أن مشكلات الخصوبة لدى الرجال تسهم في نحو نصف حالات العقم، لا يزال كثير منهم يشعرون بأنهم خارج دائرة التشخيص والعلاج. فما أسباب هذا التهميش، وكيف يمكن تغيير النظرة إلى العقم باعتباره قضية تخص صحة الرجال أيضاً؟",
      "url": "https://www.bbc.com/arabic/articles/crelxyp190no",
      "urlToImage": "https://ichef.bbci.co.uk/news/1200/branded_arabic/a894/live/2b6a9b10-7182-11f1-8546-8f19e4fe30f4.jpg",
      "publishedAt": "2026-06-26T19:01:19Z",
      "content": "Getty Images\r\nArticle Information<ul><li></li><li></li><li></li></ul>\r\n 2020 .\r\n: \" : . . \".\r\n 18 .\r\n .\r\n: \" . \".\r\n.\r\n: \" : \".\r\n .\r\n() 12 .\r\n .\r\n : \" \".\r\n 2019 .\r\n .\r\n: \" \".\r\n \" \".\r\n .\r\n 1978 .\r\n \" \"… [+674 chars]"
    },
    {
      "source": {
        "id": "cnn",
        "name": "CNN"
      },
      "author": "CNN بالعربية",
      "title": "نوادي القراءة الصامتة.. كيف تدعم صحة الدماغ وتحفّز التركيز؟",
      "description": "يقيم الأشخاص حفلات بهدف تشجيع الآخرين على القراءة من أجل المتعة. هذه اللقاءات ليست مجرد نشاط اجتماعي أو وسيلة للاسترخاء، بل يمكن أن تساعد في تحسين صحة الدماغ.",
      "url": "https://arabic.cnn.com/science-and-health/article/2026/06/25/brain-health-reading-book-club-wellness",
      "urlToImage": "https://cnn-arabic-images.cnn.io/cloudinary/image/upload/x_0,y_126,w_2497,h_1404,c_crop/w_1920,h_1008,c_fill,q_auto,g_center/t_cnnarabic_watermark_logo_v5/cnnarabic/2026/06/07/images/334551.jpg",
      "publishedAt": "2026-06-25T11:44:08Z",
      "content": "(CNN) -- \" \" . .\r\n . \r\n . .\r\n \"BookTok\" . 2025 236 \" \".\r\n \" \".\r\n 2025 \" \".\r\n. . .\r\n . : \" \".\r\n . 2020 .\r\n . 2017   .\r\n .\r\n\"Reading Rhythms\" .\r\n \" \" .\r\n : \" \".\r\n .\r\n \"Reading Rhythms\" \" \" .\r\n. : \" \".\r… [+28 chars]"
    },
    {
      "source": {
        "id": null,
        "name": "Aljazeera.net"
      },
      "author": "محمد عبد العظيم",
      "title": "الكولاجين البحري.. هل هو الحل الطبيعي لمقاومة التجاعيد؟",
      "description": "مع تزايد الاهتمام بمكملات مقاومة الشيخوخة، يبرز الكولاجين البحري بوصفه أحد أكثر الخيارات رواجا لدعم صحة البشرة، مدفوعا بدراسات تشير إلى سهولة امتصاصه وفعاليته المحتملة في الحفاظ على مرونة الجلد.",
      "url": "https://www.aljazeera.net/lifestyle/2026/6/22/%d8%a7%d9%84%d9%83%d9%88%d9%84%d8%a7%d8%ac%d9%8a%d9%86-%d8%a7%d9%84%d8%a8%d8%ad%d8%b1%d9%8a-%d9%87%d9%84-%d9%87%d9%88-%d8%a7%d9%84%d8%ad%d9%84-%d8%a7%d9%84%d8%b7%d8%a8%d9%8a%d8%b9%d9%8a",
      "urlToImage": "https://www.aljazeera.net/wp-content/uploads/2026/06/1e-1782114884.avif?resize=1200%2C675",
      "publishedAt": "2026-06-22T15:11:09Z",
      "content": "30% .\r\n .\r\nlist of 2 itemsend of list\r\n . \"\" .\r\n . .\r\n .\r\n . .\r\n . 1% .\r\n . .\r\n . 2020 12 .\r\n. .\r\n . .\r\n .\r\n .\r\n . .\r\n \"\" .\r\n 5 15 \"\" .\r\n .\r\n . .\r\n . ."
    }
  ]
}